graph_datasets/__init__.py
graph_datasets/data_info.py
graph_datasets/load_data.py
graph_datasets/datasets/__init__.py
graph_datasets/datasets/cola.py
graph_datasets/datasets/critical.py
graph_datasets/datasets/dgl.py
graph_datasets/datasets/linkx.py
graph_datasets/datasets/ogb.py
graph_datasets/datasets/pyg.py
graph_datasets/datasets/sdcn.py
graph_datasets/utils/__init__.py
graph_datasets/utils/common.py
graph_datasets/utils/logging.py
graph_datasets/utils/statistics.py
graph_datasets-1.1.1.dist-info/METADATA
graph_datasets-1.1.1.dist-info/WHEEL
graph_datasets-1.1.1.dist-info/licenses/LICENSE
graph_datasets-1.1.1.dist-info/RECORD
