Metadata-Version: 2.4
Name: graph_datasets
Version: 1.1.1
Summary: Load graph datasets.
Project-URL: Homepage, https://github.com/galogm/graph_datasets
Project-URL: Bug Tracker, https://github.com/galogm/graph_datasets/issues
Author-email: ming <gumingwork@gmail.com>
License: MIT License
License-File: LICENSE
Keywords: datasets,graph
Classifier: License :: OSI Approved :: MIT License
Classifier: Programming Language :: Python :: 3
Classifier: Topic :: Software Development :: Libraries :: Python Modules
Requires-Python: >=3.8
Requires-Dist: colorlog
Requires-Dist: dgl>=1.1.0
Requires-Dist: dglgo>=0.0.2
Requires-Dist: gdown>=4.7
Requires-Dist: pandas>=2.0.3
Requires-Dist: texttable>=1.6
Requires-Dist: torch-geometric>=2.0
Requires-Dist: torch-scatter
Requires-Dist: torch-sparse
Requires-Dist: torch>=1.12
Requires-Dist: torchaudio>=0.10.2
Requires-Dist: torchvision>=0.11.3
Requires-Dist: wget>=3.2
